README.md
setup.py
planet/__init__.py
planet/control/__init__.py
planet/control/batch_env.py
planet/control/discounted_return.py
planet/control/in_graph_batch_env.py
planet/control/mpc_agent.py
planet/control/planning.py
planet/control/random_episodes.py
planet/control/simulate.py
planet/control/wrappers.py
planet/models/__init__.py
planet/models/base.py
planet/models/rssm.py
planet/models/ssm.py
planet/networks/__init__.py
planet/networks/basic.py
planet/networks/conv_ha.py
planet/scripts/__init__.py
planet/scripts/configs.py
planet/scripts/create_video.py
planet/scripts/fetch_events.py
planet/scripts/tasks.py
planet/scripts/test_planet.py
planet/scripts/train.py
planet/tools/__init__.py
planet/tools/attr_dict.py
planet/tools/chunk_sequence.py
planet/tools/count_dataset.py
planet/tools/count_weights.py
planet/tools/custom_optimizer.py
planet/tools/filter_variables.py
planet/tools/image_strip_summary.py
planet/tools/mask.py
planet/tools/mse_distribution.py
planet/tools/nested.py
planet/tools/numpy_episodes.py
planet/tools/overshooting.py
planet/tools/preprocess.py
planet/tools/reshape_as.py
planet/tools/schedule.py
planet/tools/shape.py
planet/tools/streaming_mean.py
planet/tools/summary.py
planet/tools/test_nested.py
planet/tools/test_overshooting.py
planet/tools/unroll.py
planet/training/__init__.py
planet/training/define_model.py
planet/training/define_summaries.py
planet/training/running.py
planet/training/test_running.py
planet/training/trainer.py
planet/training/utility.py
planetrl.egg-info/PKG-INFO
planetrl.egg-info/SOURCES.txt
planetrl.egg-info/dependency_links.txt
planetrl.egg-info/requires.txt
planetrl.egg-info/top_level.txt